socklibex/__init__.py
socklibex/ex.py
socklibex/ex2.py
socklibex-0.2.dist-info/METADATA
socklibex-0.2.dist-info/WHEEL
socklibex-0.2.dist-info/top_level.txt
socklibex-0.2.dist-info/RECORD
