Metadata-Version: 2.1
Name: socklibex
Version: 0.2
Summary: Библиотека с информацией о программировании
Home-page: https://github.com/BykovskiiEgor/sockLibEx
Author: Egor
Author-email: bykovsky.egor2017@yandex.ru
